compoz/__init__.py
compoz-0.1.0b3.dist-info/LICENSE
compoz-0.1.0b3.dist-info/METADATA
compoz-0.1.0b3.dist-info/WHEEL
compoz-0.1.0b3.dist-info/RECORD
