Metadata-Version: 2.1
Name: compoz
Version: 0.1.0b3
Summary: A simple composition library
Home-page: https://github.com/haroldcohen/compoz
License: MIT
Keywords: composition,compose,functional programming
Author: Harold Cohen
Author-email: me@harold-cohen.com
Requires-Python: >=3.10,<4.0
Classifier: Development Status :: 4 - Beta
Classifier: License :: OSI Approved :: MIT License
Classifier: Operating System :: OS Independent
Classifier: Programming Language :: Python :: 3
Classifier: Programming Language :: Python :: 3.10
Classifier: Programming Language :: Python :: 3.11
Classifier: Programming Language :: Python :: 3.12
Classifier: Topic :: Scientific/Engineering :: Mathematics
Classifier: Topic :: Software Development :: Libraries :: Python Modules
Classifier: Topic :: Utilities
Project-URL: Changelog, https://github.com/haroldcohen/compoz/blob/master/CHANGELOG.md
Project-URL: Issues, https://github.com/haroldcohen/compoz/issues
Project-URL: Repository, https://github.com/haroldcohen/compoz.git
